__init__.py
t2kg/__init__.py
t2kg/models.py
t2kg/t2kg.py
t2kg/steps/_1_get_entities.py
t2kg/steps/_2_get_relations.py
t2kg/steps/_3_cluster_graph.py
t2kg/steps/__init__.py
t2kg/utils/__init__.py
t2kg/utils/chunk_text.py
t2kg-0.0.2.dist-info/METADATA
t2kg-0.0.2.dist-info/WHEEL
t2kg-0.0.2.dist-info/top_level.txt
t2kg-0.0.2.dist-info/RECORD
