Metadata-Version: 2.2
Name: t2kg
Version: 0.0.2
Summary: Extract a knowledge graph using LLMs from any text or messages array
Author-email: Belinda Mo <justanexperimentpark@gmail.com>
License: MIT
Project-URL: Homepage, https://github.com/stair-lab/t2kg
Project-URL: Issues, https://github.com/stair-lab/t2kg/issues
Classifier: Programming Language :: Python :: 3
Classifier: Programming Language :: Python :: 3.10
Classifier: Programming Language :: Python :: 3.11
Classifier: Programming Language :: Python :: 3.12
Classifier: Programming Language :: Python :: 3.13
Requires-Python: <4.0,>=3.10
